fastbotty/__init__.py
fastbotty/__version__.py
fastbotty/cli/__init__.py
fastbotty/cli/commands.py
fastbotty/core/__init__.py
fastbotty/core/bot.py
fastbotty/core/config.py
fastbotty/core/interfaces.py
fastbotty/core/registry.py
fastbotty/formatters/__init__.py
fastbotty/formatters/base.py
fastbotty/formatters/markdown.py
fastbotty/formatters/plain.py
fastbotty/server/__init__.py
fastbotty/server/app.py
fastbotty/server/routes.py
fastbotty/utils/__init__.py
fastbotty/utils/escape.py
fastbotty/utils/validators.py
fastbotty-0.0.4.dist-info/licenses/LICENSE
fastbotty-0.0.4.dist-info/METADATA
fastbotty-0.0.4.dist-info/WHEEL
fastbotty-0.0.4.dist-info/entry_points.txt
fastbotty-0.0.4.dist-info/top_level.txt
fastbotty-0.0.4.dist-info/RECORD
