Metadata-Version: 2.4
Name: fastbotty
Version: 0.0.4
Summary: Lightning-fast, super-simple Python bot framework for building powerful, interactive bots in under a minute using a single, clean YAML configuration file.
Author-email: Gemechis Chala <gladsonchala@gmail.com>
License-Expression: MIT
Project-URL: Homepage, https://github.com/venopyx/fastbotty
Project-URL: Repository, https://github.com/venopyx/fastbotty
Project-URL: Documentation, https://github.com/venopyx/fastbotty#readme
Keywords: bot,framework,yml,fast,telegram,discord,slack,email,notifications,webhook,fastapi,async,python-telegram-bot
Classifier: Development Status :: 2 - Pre-Alpha
Classifier: Intended Audience :: Developers
Classifier: Programming Language :: Python :: 3.10
Classifier: Programming Language :: Python :: 3.11
Classifier: Programming Language :: Python :: 3.12
Classifier: Programming Language :: Python :: 3.13
Classifier: Framework :: FastAPI
Classifier: Topic :: Communications :: Chat
Classifier: Topic :: Software Development :: Libraries :: Python Modules
Classifier: Typing :: Typed
Requires-Python: >=3.10
License-File: LICENSE
Requires-Dist: fastapi>=0.104.0
Requires-Dist: pydantic>=2.5.0
Requires-Dist: pydantic-settings>=2.1.0
Requires-Dist: aiohttp>=3.9.0
Requires-Dist: uvicorn[standard]>=0.30.0
Requires-Dist: pyyaml>=6.0
Requires-Dist: jinja2>=3.1.0
Requires-Dist: python-dotenv>=1.0.0
Requires-Dist: click>=8.1.0
Provides-Extra: dev
Requires-Dist: pytest>=7.4.0; extra == "dev"
Requires-Dist: pytest-asyncio>=0.21.0; extra == "dev"
Requires-Dist: pytest-cov>=4.1.0; extra == "dev"
Requires-Dist: black>=23.11.0; extra == "dev"
Requires-Dist: ruff>=0.1.6; extra == "dev"
Requires-Dist: mypy>=1.7.0; extra == "dev"
Requires-Dist: build>=1.0.0; extra == "dev"
Requires-Dist: twine>=4.0.0; extra == "dev"
Dynamic: license-file
